{
    "os": "Linux-5.15.0-73-generic-x86_64-with-glibc2.17",
    "python": "3.8.13",
    "heartbeatAt": "2023-06-13T21:50:52.135475",
    "startedAt": "2023-06-13T21:50:50.901548",
    "docker": null,
    "gpu": "NVIDIA GeForce RTX 3070 Laptop GPU",
    "gpu_count": 1,
    "cpu_count": 16,
    "cuda": null,
    "args": [
        "--weights",
        "/home/kais/workspace/pytorch-meetup/models/yolov5s.pt",
        "--device",
        "0",
        "--img",
        "1280",
        "--data",
        "exp_uniqueness/dataset.yaml",
        "--epochs",
        "50",
        "--batch-size",
        "8",
        "--patience",
        "20",
        "--nosave",
        "--project",
        "pytorch-demo",
        "--name",
        "active_uniqueness"
    ],
    "state": "running",
    "program": "/home/kais/workspace/yolov5/train.py",
    "host": "Nitro",
    "username": "kais",
    "executable": "/home/kais/anaconda3/envs/yolov5/bin/python"
}
